bridgenlp/__init__.py
bridgenlp/aligner.py
bridgenlp/base.py
bridgenlp/cli.py
bridgenlp/config.py
bridgenlp/multimodal_base.py
bridgenlp/pipeline.py
bridgenlp/result.py
bridgenlp/utils.py
bridgenlp/adapters/__init__.py
bridgenlp/adapters/adapter_template.py
bridgenlp/adapters/allen_coref.py
bridgenlp/adapters/hf_classification.py
bridgenlp/adapters/hf_embeddings.py
bridgenlp/adapters/hf_paraphrase.py
bridgenlp/adapters/hf_qa.py
bridgenlp/adapters/hf_sentiment.py
bridgenlp/adapters/hf_srl.py
bridgenlp/adapters/hf_summarization.py
bridgenlp/adapters/hf_translation.py
bridgenlp/adapters/image_captioning.py
bridgenlp/adapters/multimodal_embeddings.py
bridgenlp/adapters/nltk_adapter.py
bridgenlp/adapters/object_detection.py
bridgenlp/adapters/spacy_ner.py
bridgenlp/pipes/__init__.py
bridgenlp/pipes/spacy_pipe.py
bridgenlp-0.5.0.dist-info/licenses/LICENSE
bridgenlp-0.5.0.dist-info/METADATA
bridgenlp-0.5.0.dist-info/WHEEL
bridgenlp-0.5.0.dist-info/entry_points.txt
bridgenlp-0.5.0.dist-info/top_level.txt
bridgenlp-0.5.0.dist-info/RECORD
