Metadata-Version: 2.4
Name: bridgenlp
Version: 0.5.0
Summary: A lightweight, extensible framework for bridging advanced NLP and multimodal models with structured pipelines like spaCy, supporting text, image, and audio inputs
Author: David L Condrey
License: MIT
Project-URL: Homepage, https://github.com/dcondrey/bridgenlp
Project-URL: Repository, https://github.com/dcondrey/bridgenlp
Project-URL: Bug Tracker, https://github.com/dcondrey/bridgenlp/issues
Project-URL: Documentation, https://github.com/dcondrey/bridgenlp#readme
Classifier: Development Status :: 4 - Beta
Classifier: Environment :: Console
Classifier: Intended Audience :: Developers
Classifier: Intended Audience :: Science/Research
Classifier: License :: OSI Approved :: MIT License
Classifier: Operating System :: OS Independent
Classifier: Programming Language :: Python
Classifier: Programming Language :: Python :: 3
Classifier: Programming Language :: Python :: 3.8
Classifier: Programming Language :: Python :: 3.9
Classifier: Programming Language :: Python :: 3.10
Classifier: Topic :: Scientific/Engineering :: Artificial Intelligence
Classifier: Topic :: Text Processing :: Linguistic
Classifier: Topic :: Software Development :: Libraries
Classifier: Topic :: Utilities
Requires-Python: >=3.8
License-File: LICENSE
Requires-Dist: spacy>=3.0
Requires-Dist: numpy>=1.18
Provides-Extra: allennlp
Requires-Dist: allennlp>=2.10; extra == "allennlp"
Requires-Dist: allennlp-models>=2.10; extra == "allennlp"
Provides-Extra: huggingface
Requires-Dist: transformers>=4.25; extra == "huggingface"
Requires-Dist: torch>=1.10; extra == "huggingface"
Requires-Dist: sentencepiece; extra == "huggingface"
Requires-Dist: rich; extra == "huggingface"
Requires-Dist: langdetect>=1.0.9; extra == "huggingface"
Provides-Extra: nltk
Requires-Dist: nltk>=3.6; extra == "nltk"
Provides-Extra: multimodal
Requires-Dist: transformers>=4.25; extra == "multimodal"
Requires-Dist: torch>=1.10; extra == "multimodal"
Requires-Dist: Pillow>=9.0.0; extra == "multimodal"
Requires-Dist: timm>=0.6.0; extra == "multimodal"
Provides-Extra: all
Requires-Dist: allennlp>=2.10; extra == "all"
Requires-Dist: allennlp-models>=2.10; extra == "all"
Requires-Dist: transformers>=4.25; extra == "all"
Requires-Dist: torch>=1.10; extra == "all"
Requires-Dist: sentencepiece; extra == "all"
Requires-Dist: nltk>=3.6; extra == "all"
Requires-Dist: rich; extra == "all"
Requires-Dist: langdetect>=1.0.9; extra == "all"
Requires-Dist: Pillow>=9.0.0; extra == "all"
Requires-Dist: timm>=0.6.0; extra == "all"
Provides-Extra: dev
Requires-Dist: pytest; extra == "dev"
Requires-Dist: pytest-cov; extra == "dev"
Requires-Dist: mypy; extra == "dev"
Requires-Dist: black; extra == "dev"
Requires-Dist: isort; extra == "dev"
Requires-Dist: build; extra == "dev"
Requires-Dist: twine; extra == "dev"
Dynamic: license-file
